mem_top.py
mem_top-0.2.1.dist-info/LICENSE
mem_top-0.2.1.dist-info/METADATA
mem_top-0.2.1.dist-info/WHEEL
mem_top-0.2.1.dist-info/top_level.txt
mem_top-0.2.1.dist-info/RECORD
