Metadata-Version: 2.1
Name: mem_top
Version: 0.2.1
Summary: Shows top suspects for memory leaks in your Python program.
Home-page: https://github.com/denis-ryzhkov/mem_top
Author: Denis Ryzhkov
Author-email: denisr@denisr.com
License: MIT
Platform: UNKNOWN
Classifier: License :: OSI Approved :: MIT License
Classifier: Operating System :: OS Independent
Classifier: Programming Language :: Python :: 2.7
Classifier: Programming Language :: Python :: 3
Classifier: Topic :: Software Development :: Libraries :: Python Modules
License-File: LICENSE
